dual_auth/__init__.py
dual_auth/config.py
dual_auth/py.typed
dual_auth/adapters/__init__.py
dual_auth/adapters/auth0_adapter.py
dual_auth/adapters/base_adapter.py
dual_auth/adapters/entraid_adapter.py
dual_auth/adapters/keycloak_adapter.py
dual_auth/adapters/okta_adapter.py
dual_auth/api/__init__.py
dual_auth/api/insession_api_call.py
dual_auth/api/outofsession_api_call.py
dual_auth/session/__init__.py
dual_auth/session/hybrid_sender.py
dual_auth/session/insession_token_request.py
dual_auth/session/outofsession_token_request.py
dual_auth-1.0.1.dist-info/METADATA
dual_auth-1.0.1.dist-info/WHEEL
dual_auth-1.0.1.dist-info/top_level.txt
dual_auth-1.0.1.dist-info/RECORD
