Metadata-Version: 2.4
Name: dual-auth
Version: 1.0.1
Summary: Dual-Subject Access Control for AI Agents - A security solution implementing AGBAC for AI Agents and Humans
Author: dual-auth Project
License-Expression: Apache-2.0
Project-URL: Homepage, https://github.com/kahalewai/dual-auth
Project-URL: Documentation, https://github.com/kahalewai/dual-auth#readme
Project-URL: Repository, https://github.com/kahalewai/dual-auth
Project-URL: Issues, https://github.com/kahalewai/dual-auth/issues
Keywords: security,authentication,authorization,ai-agents,oauth,oidc,keycloak,auth0,okta,entraid,azure-ad,dual-subject,agbac
Classifier: Development Status :: 5 - Production/Stable
Classifier: Intended Audience :: Developers
Classifier: Operating System :: OS Independent
Classifier: Programming Language :: Python :: 3
Classifier: Programming Language :: Python :: 3.8
Classifier: Programming Language :: Python :: 3.9
Classifier: Programming Language :: Python :: 3.10
Classifier: Programming Language :: Python :: 3.11
Classifier: Programming Language :: Python :: 3.12
Classifier: Topic :: Security
Classifier: Topic :: Software Development :: Libraries :: Python Modules
Requires-Python: >=3.8
Requires-Dist: requests>=2.25.0
Requires-Dist: PyJWT>=2.0.0
Requires-Dist: cryptography>=3.4.0
Requires-Dist: urllib3>=1.26.0
Provides-Extra: dev
Requires-Dist: pytest>=7.0.0; extra == "dev"
Requires-Dist: pytest-cov>=4.0.0; extra == "dev"
Requires-Dist: black>=23.0.0; extra == "dev"
Requires-Dist: isort>=5.0.0; extra == "dev"
Requires-Dist: mypy>=1.0.0; extra == "dev"
Requires-Dist: flake8>=6.0.0; extra == "dev"
